setup.py
semestertask/__init__.py
semestertask/semestertask.py
semestertask.egg-info/PKG-INFO
semestertask.egg-info/SOURCES.txt
semestertask.egg-info/dependency_links.txt
semestertask.egg-info/entry_points.txt
semestertask.egg-info/requires.txt
semestertask.egg-info/top_level.txt