Metadata-Version: 1.1
Name: semestertask
Version: 1.0.2
Summary: semester-centric task generation script for taskwarrior
Home-page: https://github.com/peadargrant/semestertask
Author: Peadar Grant
Author-email: peadargrant@gmail.com
License: GPLv3+
Keywords: taskwarrior
Platform: UNKNOWN
Classifier: Development Status :: 3 - Alpha
Classifier: Intended Audience :: Education
Classifier: Topic :: Software Development :: Build Tools
Classifier: License :: OSI Approved :: GNU General Public License v3 or later (GPLv3+)
Classifier: Programming Language :: Python :: 3.5
